exercise02/CBC_cipher/cbc_cipher.sv
module cbc_cipher #(parameter n = 2, parameter m = 4) (
    input logic enc_dec,            // 1=encrypt, 0=decrypt
    input logic [8*n*m-1:0] message,
    input logic [8*n-1:0] key,
    output logic [8*n*m-1:0] result
);

    logic [8*n-1:0] block;
    logic [8*n-1:0] prev;
    logic [8*n-1:0] xor_out;

    integer i;
    always_comb begin
        prev = key;
        for (i=0; i<m; i++) begin
            block = message[i*8*n +: 8*n]; 
            xor_out = block ^ prev;
            result[i*8*n +: 8*n] = xor_out;

            if (enc_dec) begin
                // Encryption
                prev = xor_out;
            end else begin
                // Decryption
                prev = block;
            end

        end
    end
endmodule

exercise02/CBC_cipher/tb_cbc_cipher.sv
module tb_cbc_cipher;
    parameter n = 2;
    parameter m = 2;

    logic enc_dec;
    logic [8*n*m-1:0] message;
    logic [8*n-1:0] key;
    logic [8*n*m-1:0] result;

    cbc_cipher #(n, m) uut (
        .enc_dec(enc_dec),
        .message(message),
        .key(key),
        .result(result)
    );

    initial begin
        $dumpfile("cbc_cipher.vcd");
        $dumpvars(0, tb_cbc_cipher);

        // Test case 1
        key = 16'h1111;
        message = {
            8'h11, 8'h22,
            8'h33, 8'h44
        };
        
        enc_dec = 1'b1;     // Encrypt
        #1;

        enc_dec = 1'b0;     // Decrypt
        message = result;
        #1;

        // Test case 2
        key = 16'h2222;
        message = {
            8'h10, 8'h20,
            8'h30, 8'h40
        };
        
        enc_dec = 1'b1;     // Encrypt
        #1;

        enc_dec = 1'b0;     // Decrypt
        message = result;
        #1;

        // Test case 3
        key = 16'h9999;
        message = {
            8'hAA, 8'hBB,
            8'hCC, 8'hDD
        };
        
        enc_dec = 1'b1;     // Encrypt
        #1;

        enc_dec = 1'b0;     // Decrypt
        message = result;
        #1;

        // Test case 4
        key = 16'hAAAA;
        message = {
            8'h00, 8'h00,
            8'h00, 8'h00
        };
        
        enc_dec = 1'b1;     // Encrypt
        #1;

        enc_dec = 1'b0;     // Decrypt
        message = result;
        #1;  

        // Test case 5
        key = 16'hCCCC;
        message = {
            8'h19, 8'h29,
            8'h39, 8'h49
        };
        
        enc_dec = 1'b1;     // Encrypt
        #1;

        enc_dec = 1'b0;     // Decrypt
        message = result;
        #1;      

        $finish;
    end
endmodule

exercise02/CBC_cipher/cbc_cipher.vcd
$date
    May 18, 2025  17:24:40
$end
$comment
	SimVision SST: 4c533407f939851cb844a6d0dba1b3d2
$end
$version
    TOOL:	xmsim(64)	22.09-s007
$end
$timescale
    1 fs
$end

$scope module tb_cbc_cipher $end
$var parameter 32 !    n $end
$var parameter 32 "    m $end
$var reg       1 #    enc_dec $end
$var reg      32 $    message [31:0] $end
$var reg      16 %    key [15:0] $end
$var reg      32 &    result [31:0] $end

$scope module uut $end
$var parameter 32 '    n $end
$var parameter 32 (    m $end
$var wire      1 )    enc_dec  $end
$var wire     32 *    message [31:0] $end
$var wire     16 +    key [15:0] $end
$var reg      32 ,    result [31:0] $end
$var reg      16 -    block [15:0] $end
$var reg      16 .    prev [15:0] $end
$var reg      16 /    xor_out [15:0] $end
$var integer  32 0    i $end
$upscope $end

$upscope $end

$enddefinitions $end
$dumpvars
b10 (
b10 '
b10 "
b10 !
1#
b10001001000100011001101000100 $
b1000100010001 %
b110011011101110010001001010101 &
1)
b10001001000100011001101000100 *
b1000100010001 +
b110011011101110010001001010101 ,
b1000100100010 -
b11001101110111 .
b11001101110111 /
b10 0
$end
#1000
0#
b110011011101110010001001010101 $
b110011011101110010001001010101 *
0)
b1000100010001 .
b0 0
b10001001010101 -
b11001101000100 /
b110011011101110011001101000100 ,
b10001001010101 .
b1 0
b11001101110111 -
b1000100100010 /
b10001001000100011001101000100 ,
b11001101110111 .
b10 0
b10001001000100011001101000100 &
#2000
b10001000100010 %
b10000001000000011000001000000 $
1#
1)
b10000001000000011000001000000 *
b10001000100010 +
b10001000100010 .
b0 0
b11000001000000 -
b1001001100010 /
b10001001000100001001001100010 ,
b1001001100010 .
b1 0
b1000000100000 -
b1001000010 /
b10010000100001001001100010 ,
b1001000010 .
b10 0
b10010000100001001001100010 &
#3000
0#
b10010000100001001001100010 $
b10010000100001001001100010 *
0)
b10001000100010 .
b0 0
b1001001100010 -
b11000001000000 /
b10010000100011000001000000 ,
b1001001100010 .
b1 0
b1001000010 -
b1000000100000 /
b10000001000000011000001000000 ,
b1001000010 .
b10 0
b10000001000000011000001000000 &
#4000
b1001100110011001 %
b10101010101110111100110011011101 $
1#
1)
b10101010101110111100110011011101 *
b1001100110011001 +
b1001100110011001 .
b0 0
b1100110011011101 -
b101010101000100 /
b10000001000000101010101000100 ,
b101010101000100 .
b1 0
b1010101010111011 -
b1111111111111111 /
b11111111111111110101010101000100 ,
b1111111111111111 .
b10 0
b11111111111111110101010101000100 &
#5000
0#
b11111111111111110101010101000100 $
b11111111111111110101010101000100 *
0)
b1001100110011001 .
b0 0
b101010101000100 -
b1100110011011101 /
b11111111111111111100110011011101 ,
b101010101000100 .
b1 0
b1111111111111111 -
b1010101010111011 /
b10101010101110111100110011011101 ,
b1111111111111111 .
b10 0
b10101010101110111100110011011101 &
#6000
b1010101010101010 %
b0 $
1#
1)
b0 *
b1010101010101010 +
b1010101010101010 .
b0 0
b0 -
b1010101010101010 /
b10101010101110111010101010101010 ,
b1 0
b10101010101010101010101010101010 ,
b10 0
b10101010101010101010101010101010 &
#7000
0#
b10101010101010101010101010101010 $
b10101010101010101010101010101010 *
0)
b0 0
b1010101010101010 -
b0 /
b10101010101010100000000000000000 ,
b1 0
b0 ,
b10 0
b0 &
#8000
b1100110011001100 %
b11001001010010011100101001001 $
1#
1)
b11001001010010011100101001001 *
b1100110011001100 +
b1100110011001100 .
b0 0
b11100101001001 -
b1111010110000101 /
b1111010110000101 ,
b1111010110000101 .
b1 0
b1100100101001 -
b1110110010101100 /
b11101100101011001111010110000101 ,
b1110110010101100 .
b10 0
b11101100101011001111010110000101 &
#9000
0#
b11101100101011001111010110000101 $
b11101100101011001111010110000101 *
0)
b1100110011001100 .
b0 0
b1111010110000101 -
b11100101001001 /
b11101100101011000011100101001001 ,
b1111010110000101 .
b1 0
b1110110010101100 -
b1100100101001 /
b11001001010010011100101001001 ,
b1110110010101100 .
b10 0
b11001001010010011100101001001 &
