exercise05/avgm/avg.sv
module avg (
  input logic rst_ni,
  input logic clk_i,
  input logic [7 : 0] data_i,
  output logic [7 : 0] data_o
);

  logic signed [7 : 0] val1, val2, val3;

  always_ff @(posedge clk_i or negedge rst_ni) begin
    if (!rst_ni) begin
      val1 <= 0;
      val2 <= 0;
      val3 <= 0;
      data_o <= 0;
    end else begin
      // shift values
      val3 <= val2; 
      val2 <= val1; 
      val1 <= signed'(data_i);

      // average 
      data_o <= unsigned'((val1 + val2 + val3) / 3);
    end
  end 
endmodule

exercise05/avgm/tb_avgm.sv
module tb_avgm;

  logic clk_i = 0;
  logic rst_ni;
  logic [7:0] data_i;
  logic signed [7:0] avg_o; // unsigned in real usage

  avg i_dut (
      .rst_ni(rst_ni),
      .clk_i(clk_i),
      .data_i(data_i),
      .data_o(avg_o)
  );

  // Clock generation
  always #(2ns) clk_i = ~clk_i;

  initial begin
    rst_ni = 'b0;
    data_i = 0;
    #(10ns);
    rst_ni = 'b1;

    // Test cases
    @(posedge clk_i); data_i = 10;    // expect avg_o = 3
    @(posedge clk_i); data_i = 20;    // expect avg_o = 10
    @(posedge clk_i); data_i = -30;   // expect avg_o = 0
    @(posedge clk_i); data_i = -50;   // expect avg_o = -20
    @(posedge clk_i); data_i = 50;    // expect avg_o = -10
    @(posedge clk_i); data_i = 30;    // expect avg_o = 10
    @(posedge clk_i); data_i = 100;   // expect avg_o = 60
    @(posedge clk_i); data_i = -100;  // expect avg_o = 10
    @(posedge clk_i); data_i = -120;  // expect avg_o = -40
    @(posedge clk_i); data_i = -20;   // expect avg_o = -80
    @(posedge clk_i); data_i = 110;   // expect avg_o = -10
    @(posedge clk_i); data_i = 60;    // expect avg_o = 50
    @(posedge clk_i); data_i = -50;  // expect avg_o = 40
    @(posedge clk_i); data_i = 10;   // expect avg_o = 6
    @(posedge clk_i); data_i = 50;    // expect avg_o = 3
    @(posedge clk_i); data_i = 0;    // expect avg_o = 20
    repeat(2) @(posedge clk_i);    
    $finish;
  end
endmodule

exercise05/avgm/avgm.vcd
$date
    Jun  4, 2025  16:13:02
$end
$comment
	SimVision SST: 4c533407f939851cb844a6d0dba1b3d2
$end
$version
    TOOL:	xmsim(64)	22.09-s007
$end
$timescale
    1 fs
$end

$scope module tb_avgm $end
$var reg       1 !    clk_i $end
$var reg       1 "    rst_ni $end
$var reg       8 #    data_i [7:0] $end
$var reg       8 $    avg_o [7:0] $end

$scope module i_dut $end
$var wire      1 %    rst_ni  $end
$var wire      1 &    clk_i  $end
$var wire      8 '    data_i [7:0] $end
$var reg       8 (    data_o [7:0] $end
$var reg       8 )    val1 [7:0] $end
$var reg       8 *    val2 [7:0] $end
$var reg       8 +    val3 [7:0] $end
$upscope $end

$upscope $end

$enddefinitions $end
$dumpvars
0!
0"
b0 #
b0 $
0%
0&
b0 '
b0 (
b0 )
b0 *
b0 +
$end
#2000000
1!
1&
#4000000
0!
0&
#6000000
1!
1&
#8000000
0!
0&
#10000000
1"
1!
b1010 #
b1010 '
1&
1%
b1010 )
#12000000
0!
0&
#14000000
1!
b10100 #
b10100 '
1&
b1010 *
b10100 )
b11 (
b11 $
#16000000
0!
0&
#18000000
1!
b11100010 #
b11100010 '
1&
b1010 +
b10100 *
b11100010 )
b1010 (
b1010 $
#20000000
0!
0&
#22000000
1!
b11001110 #
b11001110 '
1&
b10100 +
b11100010 *
b11001110 )
b0 (
b0 $
#24000000
0!
0&
#26000000
1!
b110010 #
b110010 '
1&
b11100010 +
b11001110 *
b110010 )
b11101100 (
b11101100 $
#28000000
0!
0&
#30000000
1!
b11110 #
b11110 '
1&
b11001110 +
b110010 *
b11110 )
b11110110 (
b11110110 $
#32000000
0!
0&
#34000000
1!
b1100100 #
b1100100 '
1&
b110010 +
b11110 *
b1100100 )
b1010 (
b1010 $
#36000000
0!
0&
#38000000
1!
b10011100 #
b10011100 '
1&
b11110 +
b1100100 *
b10011100 )
b111100 (
b111100 $
#40000000
0!
0&
#42000000
1!
b10001000 #
b10001000 '
1&
b1100100 +
b10011100 *
b10001000 )
b1010 (
b1010 $
#44000000
0!
0&
#46000000
1!
b11101100 #
b11101100 '
1&
b10011100 +
b10001000 *
b11101100 )
b11011000 (
b11011000 $
#48000000
0!
0&
#50000000
1!
b1101110 #
b1101110 '
1&
b10001000 +
b11101100 *
b1101110 )
b10110000 (
b10110000 $
#52000000
0!
0&
#54000000
1!
b111100 #
b111100 '
1&
b11101100 +
b1101110 *
b111100 )
b11110110 (
b11110110 $
#56000000
0!
0&
#58000000
1!
b11001110 #
b11001110 '
1&
b1101110 +
b111100 *
b11001110 )
b110010 (
b110010 $
#60000000
0!
0&
#62000000
1!
b1010 #
b1010 '
1&
b111100 +
b11001110 *
b1010 )
b101000 (
b101000 $
#64000000
0!
0&
#66000000
1!
b110010 #
b110010 '
1&
b11001110 +
b1010 *
b110010 )
b110 (
b110 $
#68000000
0!
0&
#70000000
1!
b0 #
b0 '
1&
b1010 +
b110010 *
b0 )
b11 (
b11 $
#72000000
0!
0&
#74000000
1!
1&
b110010 +
b0 *
b10100 (
b10100 $
